net_queue/__init__.py
net_queue/asynctools.py
net_queue/client.py
net_queue/server.py
net_queue/stream.py
net_queue/grpc/__init__.py
net_queue/grpc/client.py
net_queue/grpc/server.py
net_queue/mqtt/__init__.py
net_queue/mqtt/client.py
net_queue/mqtt/server.py
net_queue/tcp/__init__.py
net_queue/tcp/client.py
net_queue/tcp/server.py
net_queue-1.0.0.dist-info/licenses/LICENSE
net_queue-1.0.0.dist-info/METADATA
net_queue-1.0.0.dist-info/WHEEL
net_queue-1.0.0.dist-info/top_level.txt
net_queue-1.0.0.dist-info/RECORD
