Metadata-Version: 2.4
Name: net-queue
Version: 1.0.0
Summary: Easy & fast network communications using queues
Author-email: Miguel Ángel Prosper <mprosper@uji.es>
License-Expression: GPL-3.0-or-later
Project-URL: Homepage, https://github.com/hpca-uji/net-queue
Project-URL: Repository, https://github.com/hpca-uji/net-queue.git
Keywords: Communication,Protocol,Python
Classifier: Development Status :: 5 - Production/Stable
Classifier: Intended Audience :: Developers
Classifier: Programming Language :: Python :: 3 :: Only
Classifier: Programming Language :: Python :: 3.13
Classifier: Topic :: System :: Networking
Classifier: Topic :: Software Development :: Libraries :: Python Modules
Classifier: Topic :: Utilities
Requires-Python: >=3.13
License-File: LICENSE
Requires-Dist: bidict>=0.23.1
Requires-Dist: grpcio>=1.74.0
Requires-Dist: paho-mqtt>=2.1.0
Provides-Extra: test
Requires-Dist: numpy>=1.19.4; extra == "test"
Dynamic: license-file
